helloPackage/HelloNoor.py
helloPackage/__init__.py
helloNoor-0.0.3.dist-info/METADATA
helloNoor-0.0.3.dist-info/WHEEL
helloNoor-0.0.3.dist-info/top_level.txt
helloNoor-0.0.3.dist-info/RECORD
