Metadata-Version: 2.1
Name: helloNoor
Version: 0.0.3
Summary: Saying hi to Noor
Home-page: UNKNOWN
Author: Noor Hashem
Author-email: noor.hashem@hotmail.com
License: UNKNOWN
Keywords: python
Platform: UNKNOWN
Classifier: Development Status :: 1 - Planning
Classifier: Intended Audience :: Developers
Classifier: Programming Language :: Python :: 3
Classifier: Operating System :: Unix
Classifier: Operating System :: MacOS :: MacOS X
Classifier: Operating System :: Microsoft :: Windows
